tubez/__init__.py
tubez/cli.py
tubez/queue_manager.py
tubez/server.py
tubez/static/style.css
tubez/templates/base.html
tubez/templates/files.html
tubez/templates/formats.html
tubez/templates/index.html
tubez/templates/login.html
tubez/templates/play.html
tubez/templates/playlist.html
tubez/templates/progress.html
tubez/templates/results.html
tubez/templates/settings.html
tubez/templates/share.html
tubez-1.0.9.dist-info/licenses/LICENSE
tubez-1.0.9.dist-info/METADATA
tubez-1.0.9.dist-info/WHEEL
tubez-1.0.9.dist-info/entry_points.txt
tubez-1.0.9.dist-info/top_level.txt
tubez-1.0.9.dist-info/RECORD
